{"BatchSize":4,"SerializedLayers":[{"Bias":[-0.92110407911744,0.4291105297132535],"Weights":[[0.9207416869152576,-1.3018025340163655],[0.9380249351273636,-2.1235010089137383]],"ActivatorType":"LeakyReLU","GradientAdjustmentParameters":{"LearningRate":1,"Type":"FixedLearningRate"},"Type":"Standard"},{"Bias":[0.9798584611488593],"Weights":[[-1.1203093167219085],[-2.3075129217210093]],"ActivatorType":"LeakyReLU","GradientAdjustmentParameters":{"LearningRate":1,"Type":"FixedLearningRate"},"Type":"Standard"}]}